DeepRegressionEnsembles/__init__.py
DeepRegressionEnsembles/data.py
DeepRegressionEnsembles/models.py
DeepRegressionEnsembles-0.2.dist-info/LICENSE.txt
DeepRegressionEnsembles-0.2.dist-info/METADATA
DeepRegressionEnsembles-0.2.dist-info/WHEEL
DeepRegressionEnsembles-0.2.dist-info/top_level.txt
DeepRegressionEnsembles-0.2.dist-info/RECORD
